pyd3d12/D3D12.py
pyd3d12/D3D12_2.py
pyd3d12/OLE.py
pyd3d12/__init__.py
pyd3d12/compatibility_2.py
pyd3d12/d3d12compatibility.py
pyd3d12/d3d12sdklayers.py
pyd3d12/d3d12sdklayers_2.py
pyd3d12/dll.py
pyd3d12/stdole.py
PyD3D12-2.1.7.dist-info/LICENSE
PyD3D12-2.1.7.dist-info/METADATA
PyD3D12-2.1.7.dist-info/WHEEL
PyD3D12-2.1.7.dist-info/top_level.txt
PyD3D12-2.1.7.dist-info/RECORD
