Metadata-Version: 2.1
Name: PyD3D12
Version: 2.1.7
Summary: A 1:1 raw Python binding to Direct3D 12
Author-email: WCG847 <heelmods@gmail.com>
License: Apache-2.0
Project-URL: Homepage, https://github.com/wcg847/PyD3D12
Project-URL: Repository, https://github.com/wcg847/PyD3D12
Platform: Windows
Classifier: Operating System :: Microsoft :: Windows
Classifier: Programming Language :: Python :: 3
Classifier: Programming Language :: Python :: 3.8
Classifier: Programming Language :: Python :: 3.9
Classifier: Programming Language :: Python :: 3.10
Classifier: Programming Language :: Python :: 3.11
Classifier: Intended Audience :: Developers
Classifier: License :: OSI Approved :: Apache Software License
Classifier: Topic :: Software Development :: Libraries
Classifier: Topic :: Games/Entertainment :: Simulation
Requires-Python: >=3.8
License-File: LICENSE
